setup.cfg
setup.py
MicroblogCrawler.egg-info/SOURCES.txt
microblogcrawler/__init__.py
microblogcrawler/crawler.py
microblogcrawler.egg-info/PKG-INFO
microblogcrawler.egg-info/SOURCES.txt
microblogcrawler.egg-info/dependency_links.txt
microblogcrawler.egg-info/requires.txt
microblogcrawler.egg-info/top_level.txt
test/__init__.py
test/microblog_test.py
test/on_demand_test.py
test/rss_test.py
test/stop_immediatly_test.py