Metadata-Version: 1.0
Name: MicroblogCrawler
Version: 1.4.1
Summary: A basic microblog/rss feed crawler modeled after the Tweepy StreamListener.
Home-page: https://github.com/Sonictherocketman/microblog_feedcrawler
Author: Brian Schrader
Author-email: brian@biteofanapple.com
License: LICENSE.txt
Keywords: microblog,crawler,rss
Platform: UNKNOWN
